<?xml version="1.0" encoding="utf-8"?>
<PluginAssembly FullName="Paz.LuckeyMonkey.Plugin.Account, Version=1.0.0.0, Culture=en, PublicKeyToken=8a7d5e3a2612a23d" PluginAssemblyId="268b2631-fb3a-e911-a830-000d3a19c80e" CustomizationLevel="1">
  <IsolationMode>2</IsolationMode>
  <SourceType>0</SourceType>
  <IntroducedVersion>1.0</IntroducedVersion>
  <FileName>/PluginAssemblies/PazLuckeyMonkeyPluginAccount-268B2631-FB3A-E911-A830-000D3A19C80E/PazLuckeyMonkeyPluginAccount.dll</FileName>
  <PluginTypes>
    <PluginType AssemblyQualifiedName="Paz.LuckeyMonkey.PluginAccount.PreAccountCreateSynchronous, Paz.LuckeyMonkey.Plugin.Account, Version=1.0.0.0, Culture=en, PublicKeyToken=8a7d5e3a2612a23d" PluginTypeId="e4ef4535-fb3a-e911-a81f-000d3a17c02e" Name="Paz.LuckeyMonkey.PluginAccount.PreAccountCreateSynchronous">
      <FriendlyName>Paz.LuckeyMonkey.PluginAccount.PreAccountCreateSynchronous</FriendlyName>
    </PluginType>
  </PluginTypes>
</PluginAssembly>